setup_cronjob/__init__.py
setup_cronjob/cli.py
setup_cronjob/cron.tmpl
setup_cronjob/lib.py
setup_cronjob/logging.py
setup_cronjob/logrotate.tmpl
setup_cronjob/py.typed
setup_cronjob/settings.py
dycw_setup_cronjob-0.3.5.dist-info/WHEEL
dycw_setup_cronjob-0.3.5.dist-info/entry_points.txt
dycw_setup_cronjob-0.3.5.dist-info/METADATA
dycw_setup_cronjob-0.3.5.dist-info/RECORD
