Metadata-Version: 2.3
Name: dycw-setup-cronjob
Version: 0.3.5
Summary: Library to set up cron jobs
Author: Derek Wan
Author-email: Derek Wan <d.wan@icloud.com>
Requires-Dist: click>=8.3.1,<9
Requires-Dist: dycw-utilities>=0.172.3,<1
Requires-Dist: typed-settings[attrs,click]>=25.3.0,<26
Requires-Python: >=3.14
